documentdataextraction/Document_Automated_Training.py
documentdataextraction/Gemini_input_module.py
documentdataextraction/GenerateExtractTemplate.py
documentdataextraction/GoogleCloudAIDataExtractor.py
documentdataextraction/OpenAIDataExtractor.py
documentdataextraction/__init__.py
documentdataextraction/data_extractor.py
documentdataextraction/fitz_input_module.py
documentdataextraction-0.0.165.dist-info/LICENCE.txt
documentdataextraction-0.0.165.dist-info/METADATA
documentdataextraction-0.0.165.dist-info/WHEEL
documentdataextraction-0.0.165.dist-info/top_level.txt
documentdataextraction-0.0.165.dist-info/RECORD
