Metadata-Version: 2.1
Name: documentdataextraction
Version: 0.0.165
Summary: Resolved the FileNotFound error that occurred when Excel files failed to convert to PDF due to .xls files actually being internally in .xlsx format.
Author: Proteus Technology PVT. LTD.
Author-email: <apps@baseinformation.com>
Keywords: python,first package
Classifier: Development Status :: 3 - Alpha
Classifier: Intended Audience :: Education
Classifier: Programming Language :: Python :: 2
Classifier: Programming Language :: Python :: 3
Classifier: Operating System :: MacOS :: MacOS X
Classifier: Operating System :: Microsoft :: Windows
License-File: LICENCE.txt
Requires-Dist: pdf2image
Requires-Dist: invoice2data
Requires-Dist: readchequeutility
Requires-Dist: fitz
Requires-Dist: pathlib
Requires-Dist: pdfkit
Requires-Dist: flask
Requires-Dist: pdfplumber
Requires-Dist: PyYAML
Requires-Dist: google-cloud-documentai ==2.13.0
Requires-Dist: striprtf
Requires-Dist: docx2txt
Requires-Dist: tiktoken
